{"name":"8f407a06-9c7e-617c-8dc5-cf4c2e811949","id":"/providers/Microsoft.Flow/flows/8f407a06-9c7e-617c-8dc5-cf4c2e811949","type":"Microsoft.Flow/flows","properties":{"apiId":"/providers/Microsoft.PowerApps/apis/shared_logicflows","displayName":"createContractFile","definition":{"metadata":{"workflowEntityId":"32f8f35d-83a2-ee11-be37-000d3a2d29bc","processAdvisorMetadata":null,"flowChargedByPaygo":null,"flowclientsuspensionreason":"None","flowclientsuspensiontime":null,"flowclientsuspensionreasondetails":null,"creator":{"id":"7ca1e9bf-54ba-4f5c-980f-4077d287197e","type":"User","tenantId":"aec0543a-cc73-4fa4-9e2a-cf52adf9b788"},"provisioningMethod":"FromDefinition","failureAlertSubscription":true,"clientLastModifiedTime":"2024-01-30T10:31:19.2559205Z","connectionKeySavedTimeKey":"2024-01-30T10:31:19.2559205Z"},"$schema":"https://schema.management.azure.com/providers/Microsoft.Logic/schemas/2016-06-01/workflowdefinition.json#","contentVersion":"1.0.0.0","parameters":{"$connections":{"defaultValue":{},"type":"Object"},"$authentication":{"defaultValue":{},"type":"SecureObject"}},"triggers":{"manual":{"metadata":{"operationMetadataId":"cede1764-4ab0-4f5e-b809-0e232425c640"},"type":"Request","kind":"PowerAppV2","inputs":{"schema":{"type":"object","properties":{"number":{"title":"ContractID","type":"number","x-ms-dynamically-added":true,"description":"Please enter a number","x-ms-content-hint":"NUMBER"},"number_1":{"title":"DistID","type":"number","x-ms-dynamically-added":true,"description":"Please enter a number","x-ms-content-hint":"NUMBER"}},"required":["number","number_1"]}}}},"actions":{"Get_Dist":{"runAfter":{"Initialize_totalSales":["Succeeded"]},"metadata":{"operationMetadataId":"1a6ee24e-52fd-47c4-ba13-2a1916506100"},"type":"OpenApiConnection","inputs":{"host":{"apiId":"/providers/Microsoft.PowerApps/apis/shared_sharepointonline","connectionName":"shared_sharepointonline","operationId":"GetItem"},"parameters":{"dataset":"https://biomerieux.sharepoint.com/sites/Clinical_Operations-China_Distributor_territory-China","table":"8d32f300-2e1e-438e-9d31-e20010fb60c8","id":"@triggerBody()['number_1']"},"authentication":{"value":"@json(decodeBase64(triggerOutputs().headers['X-MS-APIM-Tokens']))['$ConnectionKey']","type":"Raw"}}},"Get_contract":{"runAfter":{"Get_Dist":["Succeeded"]},"metadata":{"operationMetadataId":"c4e9f198-3261-432a-91e8-b9c2ba398f23"},"type":"OpenApiConnection","inputs":{"host":{"apiId":"/providers/Microsoft.PowerApps/apis/shared_sharepointonline","connectionName":"shared_sharepointonline","operationId":"GetItem"},"parameters":{"dataset":"https://biomerieux.sharepoint.com/sites/Clinical_Operations-China_Distributor_territory-China","table":"74bbee9c-d61e-4b61-968b-639f880e7e25","id":"@triggerBody()['number']"},"authentication":{"value":"@json(decodeBase64(triggerOutputs().headers['X-MS-APIM-Tokens']))['$ConnectionKey']","type":"Raw"}}},"Get_contract_items":{"runAfter":{"Apply_to_each_file":["Succeeded"]},"metadata":{"operationMetadataId":"971829da-562d-47c8-8f15-f42c87eb63be"},"type":"OpenApiConnection","inputs":{"host":{"apiId":"/providers/Microsoft.PowerApps/apis/shared_sharepointonline","connectionName":"shared_sharepointonline","operationId":"GetItems"},"parameters":{"dataset":"https://biomerieux.sharepoint.com/sites/Clinical_Operations-China_Distributor_territory-China","table":"41e1e02b-eadd-4c3a-b251-2318b1fbff1f","$filter":"Contract/Title eq '@{outputs('Get_contract')?['body/Title']}'","$orderby":"Region asc, BIN asc"},"authentication":{"value":"@json(decodeBase64(triggerOutputs().headers['X-MS-APIM-Tokens']))['$ConnectionKey']","type":"Raw"}}},"Get_sales":{"runAfter":{"Select_contract_item":["Succeeded"]},"metadata":{"operationMetadataId":"78640910-3986-4e2f-b670-2e246de7fd66"},"type":"OpenApiConnection","inputs":{"host":{"apiId":"/providers/Microsoft.PowerApps/apis/shared_sharepointonline","connectionName":"shared_sharepointonline","operationId":"GetItems"},"parameters":{"dataset":"https://biomerieux.sharepoint.com/sites/Clinical_Operations-China_Distributor_territory-China","table":"5c098f06-ce5c-4736-8cad-d2b0519a7c28","$filter":"Distributor/Title eq '@{outputs('Get_Dist')?['body/Title']}'"},"authentication":{"value":"@json(decodeBase64(triggerOutputs().headers['X-MS-APIM-Tokens']))['$ConnectionKey']","type":"Raw"}}},"Create_file":{"runAfter":{"Condition":["Succeeded"]},"metadata":{"operationMetadataId":"65b87033-ea40-400f-9afe-44a88ad1f71f"},"type":"OpenApiConnection","inputs":{"host":{"apiId":"/providers/Microsoft.PowerApps/apis/shared_sharepointonline","connectionName":"shared_sharepointonline","operationId":"CreateFile"},"parameters":{"dataset":"https://biomerieux.sharepoint.com/sites/Clinical_Operations-China_Distributor_territory-China","folderPath":"/Shared Documents/General/contract-doc","name":"@outputs('Compose_fname')","body":"@body('Populate_a_Microsoft_Word_template_2')"},"authentication":{"value":"@json(decodeBase64(triggerOutputs().headers['X-MS-APIM-Tokens']))['$ConnectionKey']","type":"Raw"}},"runtimeConfiguration":{"contentTransfer":{"transferMode":"Chunked"}}},"Initialize_salesBudget":{"runAfter":{"Initialize_contract_item":["Succeeded"]},"metadata":{"operationMetadataId":"ad7853b0-21ad-402d-8355-e7cee49da0fc"},"type":"InitializeVariable","inputs":{"variables":[{"name":"salesBudget","type":"array"}]}},"Initialize_contract_item":{"runAfter":{"Initialize_flowSuccess":["Succeeded"]},"metadata":{"operationMetadataId":"6389fdbf-2a41-4ff2-99ad-5ca90266c1bf"},"type":"InitializeVariable","inputs":{"variables":[{"name":"contractItem","type":"array"}]}},"Apply_to_each_contract_item":{"foreach":"@outputs('Get_contract_items')?['body/value']","actions":{"Append_to_array_contract_item":{"runAfter":{},"metadata":{"operationMetadataId":"2d6bb169-0f65-43a6-ad23-6f0b4735eea1"},"type":"AppendToArrayVariable","inputs":{"name":"contractItem","value":{"region":"@{items('Apply_to_each_contract_item')?['Region/Value']}  @{items('Apply_to_each_contract_item')?['field_3/Value']} : @{items('Apply_to_each_contract_item')?['field_4']}   ","productType":"@items('Apply_to_each_contract_item')?['BIN/Value']","line":"@{items('Apply_to_each_contract_item')?['SBS']}, \n产品线范围： @{items('Apply_to_each_contract_item')?['LineScope/Value']}@{items('Apply_to_each_contract_item')?['ProductLine0']}, \n产品范围： @{items('Apply_to_each_contract_item')?['field_7/Value']}:  @{items('Apply_to_each_contract_item')?['field_8']} ，\n医院范围：@{items('Apply_to_each_contract_item')?['HospitalOp/Value']} @{items('Apply_to_each_contract_item')?['Hosptial']}，\n 科室范围：@{items('Apply_to_each_contract_item')?['DepartmentOp/Value']} @{items('Apply_to_each_contract_item')?['Department']}"}}}},"runAfter":{"Get_contract_items":["Succeeded"]},"metadata":{"operationMetadataId":"a4026374-1e7a-4277-af54-f0a50253ddf5"},"type":"Foreach"},"Select_contract_item":{"runAfter":{"Apply_to_each_contract_item":["Succeeded"]},"metadata":{"operationMetadataId":"995f4033-0e9d-43ec-9ead-8a6c52fd3513"},"type":"Select","inputs":{"from":"@variables('contractItem')","select":{"region":"@item()['region']","productType":"@item()['productType']","line":"@item()['Line']"}}},"Select_sales":{"runAfter":{"Apply_to_each_sales":["Succeeded"]},"metadata":{"operationMetadataId":"e8eace51-7248-432f-99ac-eec41aa94044"},"type":"Select","inputs":{"from":"@variables('salesBudget')","select":{"Product":"@item()['Product']","Region":"@item()['Region']","Q1":"@formatNumber(item()['Q1'], '0,0.00')","Q2":"@formatNumber(item()['Q2'], '0,0.00')","Q3":"@formatNumber(item()['Q3'], '0,0.00')","Q4":"@formatNumber(item()['Q4'], '0,0.00')","yearTotal":"@formatNumber(item()['yearTotal'], '0,0.00')"}}},"Apply_to_each_sales":{"foreach":"@outputs('Get_sales')?['body/value']","actions":{"Append_to_array_salesBudget":{"runAfter":{},"metadata":{"operationMetadataId":"5da663ba-d58d-4065-90af-0808d2c56b38"},"type":"AppendToArrayVariable","inputs":{"name":"salesBudget","value":{"Product":"@items('Apply_to_each_sales')?['ProductType/Value']","Region":"@items('Apply_to_each_sales')?['Region/Value']","Q1":"@items('Apply_to_each_sales')?['Quarter1']","Q2":"@items('Apply_to_each_sales')?['Quarter2']","Q3":"@items('Apply_to_each_sales')?['Quarter3']","Q4":"@items('Apply_to_each_sales')?['Quarter4']","yearTotal":"@items('Apply_to_each_sales')?['Total']"}}},"Increment_variable":{"runAfter":{"Append_to_array_salesBudget":["Succeeded"]},"metadata":{"operationMetadataId":"2cc1dbdb-4a78-438b-9c43-908022333d21"},"type":"IncrementVariable","inputs":{"name":"TotalSales","value":"@items('Apply_to_each_sales')?['Total']"}}},"runAfter":{"Get_sales":["Succeeded"]},"metadata":{"operationMetadataId":"a9575343-b38d-4b32-8dfd-861b0d075ee9"},"type":"Foreach"},"Condition":{"actions":{},"runAfter":{"Populate_a_Microsoft_Word_template_2":["Succeeded"]},"expression":{"equals":["",""]},"metadata":{"operationMetadataId":"63da8120-f232-4ec3-b73c-def3e25fb9da"},"type":"If"},"Compose_fname":{"runAfter":{"Select_company":["Succeeded"]},"metadata":{"operationMetadataId":"182f714a-7966-4efb-a933-2fe6e90d7175"},"type":"Compose","inputs":"@concat(outputs('Get_contract')?['body/Distributor/Value'],'-',outputs('Get_contract')?['body/SalesRegion/Value'],'-',outputs('Get_contract')?['body/field_5/Value'],'-',outputs('Get_contract')?['body/field_6/Value'],'.docx')"},"Get_files_(properties_only)":{"runAfter":{"Get_Clinic_Sales_plan":["Succeeded"]},"metadata":{"operationMetadataId":"93ffe47a-be7c-4828-874b-38453a43fabe"},"type":"OpenApiConnection","inputs":{"host":{"apiId":"/providers/Microsoft.PowerApps/apis/shared_sharepointonline","connectionName":"shared_sharepointonline","operationId":"GetFileItems"},"parameters":{"dataset":"https://biomerieux.sharepoint.com/sites/Clinical_Operations-China_Distributor_territory-China","table":"1cbefee5-dd57-4603-96a3-efcbe5dfbd09","folderPath":"/Shared Documents/General/contract-doc","$filter":"FileLeafRef eq  '@{outputs('Compose_fname')}'"},"authentication":{"value":"@json(decodeBase64(triggerOutputs().headers['X-MS-APIM-Tokens']))['$ConnectionKey']","type":"Raw"}}},"Apply_to_each_file":{"foreach":"@outputs('Get_files_(properties_only)')?['body/value']","actions":{"Delete_file":{"runAfter":{},"metadata":{"operationMetadataId":"a23cb63a-9d39-4a5b-bd4e-f26360c2a7a0"},"type":"OpenApiConnection","inputs":{"host":{"apiId":"/providers/Microsoft.PowerApps/apis/shared_sharepointonline","connectionName":"shared_sharepointonline","operationId":"DeleteFile"},"parameters":{"dataset":"https://biomerieux.sharepoint.com/sites/Clinical_Operations-China_Distributor_territory-China","id":"@items('Apply_to_each_file')?['{Identifier}']"},"authentication":{"value":"@json(decodeBase64(triggerOutputs().headers['X-MS-APIM-Tokens']))['$ConnectionKey']","type":"Raw"}}}},"runAfter":{"Get_files_(properties_only)":["Succeeded"]},"metadata":{"operationMetadataId":"fda275e3-4cd5-418b-af99-74e35dcb2eb9"},"type":"Foreach"},"Send_an_email_(V2)":{"runAfter":{"Get_file_content_using_path":["Succeeded"]},"metadata":{"operationMetadataId":"37794c9c-c936-4921-a7ee-4d6457473fd3"},"type":"OpenApiConnection","inputs":{"host":{"apiId":"/providers/Microsoft.PowerApps/apis/shared_office365","connectionName":"shared_office365","operationId":"SendEmailV2"},"parameters":{"emailMessage/To":"@outputs('Get_contract')?['body/Author/Email']","emailMessage/Subject":"@{outputs('Compose_fname')} 合同已创建成功","emailMessage/Body":"<p>合同文件路径<br>\n@{outputs('Create_file')?['body/Path']}</p>","emailMessage/Attachments":[{"Name":"@outputs('Compose_fname')","ContentBytes":"@body('Get_file_content_using_path')"}],"emailMessage/Importance":"Normal"},"authentication":{"value":"@json(decodeBase64(triggerOutputs().headers['X-MS-APIM-Tokens']))['$ConnectionKey']","type":"Raw"}}},"Get_file_content_using_path":{"runAfter":{"Create_file":["Succeeded"]},"metadata":{"operationMetadataId":"66cd7f0f-5a78-471f-9daf-6863e4000938"},"type":"OpenApiConnection","inputs":{"host":{"apiId":"/providers/Microsoft.PowerApps/apis/shared_sharepointonline","connectionName":"shared_sharepointonline","operationId":"GetFileContentByPath"},"parameters":{"dataset":"https://biomerieux.sharepoint.com/sites/Clinical_Operations-China_Distributor_territory-China","path":"@outputs('Create_file')?['body/Path']","inferContentType":true},"authentication":{"value":"@json(decodeBase64(triggerOutputs().headers['X-MS-APIM-Tokens']))['$ConnectionKey']","type":"Raw"}}},"Initialize_brands":{"runAfter":{"Initialize_dealerSalesTarget":["Succeeded"]},"metadata":{"operationMetadataId":"0ec41e87-6a0c-457e-8631-0c9304a11fc7"},"type":"InitializeVariable","inputs":{"variables":[{"name":"brands","type":"array"}]}},"Initialize_company":{"runAfter":{"Initialize_brands":["Succeeded"]},"metadata":{"operationMetadataId":"cb8f4e45-1de5-4b12-803e-b1714d827952"},"type":"InitializeVariable","inputs":{"variables":[{"name":"Companies","type":"array"}]}},"Initialize_totalSales":{"runAfter":{"Initialize_company":["Succeeded"]},"metadata":{"operationMetadataId":"a5818c28-b1e0-4972-a0be-5d3d02ad066b"},"type":"InitializeVariable","inputs":{"variables":[{"name":"TotalSales","type":"float","value":0}]}},"Get_brands":{"runAfter":{"Get_contract":["Succeeded"]},"metadata":{"operationMetadataId":"8fbefe2f-7bd5-4268-939a-6da7e0146a3e"},"type":"OpenApiConnection","inputs":{"host":{"apiId":"/providers/Microsoft.PowerApps/apis/shared_sharepointonline","connectionName":"shared_sharepointonline","operationId":"GetItems"},"parameters":{"dataset":"https://biomerieux.sharepoint.com/sites/Clinical_Operations-China_Distributor_territory-China","table":"2ba15cc5-c5bf-4b04-a212-53157b115138","$filter":"Distributor/Title eq '@{outputs('Get_Dist')?['body/Title']}'"},"authentication":{"value":"@json(decodeBase64(triggerOutputs().headers['X-MS-APIM-Tokens']))['$ConnectionKey']","type":"Raw"}}},"Select_brand":{"runAfter":{"Apply_to_each_brand":["Succeeded"]},"metadata":{"operationMetadataId":"ce02f184-76d9-4b26-9c13-5b27ecdb9791"},"type":"Select","inputs":{"from":"@variables('brands')","select":{"brand":"@item()['brand']","product":"@item()['product']","region":"@item()['region']"}}},"Get_company":{"runAfter":{"Select_brand":["Succeeded"]},"metadata":{"operationMetadataId":"d1ffb9db-165f-4c02-8377-3a204c4173e0"},"type":"OpenApiConnection","inputs":{"host":{"apiId":"/providers/Microsoft.PowerApps/apis/shared_sharepointonline","connectionName":"shared_sharepointonline","operationId":"GetItems"},"parameters":{"dataset":"https://biomerieux.sharepoint.com/sites/Clinical_Operations-China_Distributor_territory-China","table":"457b6003-393c-4daf-b726-945754d72b5f","$filter":"Distributor/Title eq '@{outputs('Get_Dist')?['body/Title']}'"},"authentication":{"value":"@json(decodeBase64(triggerOutputs().headers['X-MS-APIM-Tokens']))['$ConnectionKey']","type":"Raw"}}},"Apply_to_each_company":{"foreach":"@outputs('Get_company')?['body/value']","actions":{"Append_to_array_company":{"runAfter":{},"metadata":{"operationMetadataId":"e5c7a990-fe0b-4c32-b6a3-a30171cc3f0e"},"type":"AppendToArrayVariable","inputs":{"name":"Companies","value":{"RelateCompany":"@items('Apply_to_each_company')?['Company']"}}}},"runAfter":{"Get_company":["Succeeded"]},"metadata":{"operationMetadataId":"c63e95d3-2ad1-4fbd-bdca-888a277cce24"},"type":"Foreach"},"Select_company":{"runAfter":{"Apply_to_each_company":["Succeeded"]},"metadata":{"operationMetadataId":"0ef6ae49-67d5-4b36-b45e-7dcd2e34704a"},"type":"Select","inputs":{"from":"@variables('Companies')","select":{"RelateCompany":"@item()['RelateCompany']"}}},"Apply_to_each_brand":{"foreach":"@outputs('Get_brands')?['body/value']","actions":{"Append_to_array_brand":{"runAfter":{},"metadata":{"operationMetadataId":"5bbf8288-bc60-4f04-8510-77c113585757"},"type":"AppendToArrayVariable","inputs":{"name":"brands","value":{"brand":"@items('Apply_to_each_brand')?['Brand']","product":"@items('Apply_to_each_brand')?['Products']","region":"@items('Apply_to_each_brand')?['Districts']"}}}},"runAfter":{"Get_brands":["Succeeded"]},"metadata":{"operationMetadataId":"d21969d7-dfb7-4a47-8d3b-d346e2e3a3c2"},"type":"Foreach"},"Get_Clinic_Sales_plan":{"runAfter":{"Compose_fname":["Succeeded"]},"metadata":{"operationMetadataId":"bcb19dc0-51c6-4f11-acc9-405773c015e0"},"type":"OpenApiConnection","inputs":{"host":{"apiId":"/providers/Microsoft.PowerApps/apis/shared_sharepointonline","connectionName":"shared_sharepointonline","operationId":"GetItems"},"parameters":{"dataset":"https://biomerieux.sharepoint.com/sites/Clinical_Operations-China_Distributor_territory-China","table":"c478b335-f808-481b-8a2d-a0a65eb11467","$filter":"ContractID/Title eq '@{outputs('Get_contract')?['body/Title']}'"},"authentication":{"value":"@json(decodeBase64(triggerOutputs().headers['X-MS-APIM-Tokens']))['$ConnectionKey']","type":"Raw"}}},"Initialize_salesPeople":{"runAfter":{"Initialize_deviceSales":["Succeeded"]},"metadata":{"operationMetadataId":"810272e2-02ca-47ee-9dd7-4cb671909656"},"type":"InitializeVariable","inputs":{"variables":[{"name":"salesPeople","type":"array"}]}},"Initialize_strategic":{"runAfter":{"Initialize_marketPlan":["Succeeded"]},"metadata":{"operationMetadataId":"54937327-a64e-46f6-a0ec-4166b0c3788d"},"type":"InitializeVariable","inputs":{"variables":[{"name":"StrategicPlan","type":"array"}]}},"Apply_to_each_strategy_plan":{"foreach":"@outputs('Get_Clinic_Sales_plan')?['body/value']","actions":{"Append_to_array_strategy_plan":{"runAfter":{},"metadata":{"operationMetadataId":"1556887b-85e1-43b5-a981-ebb130f87875"},"type":"AppendToArrayVariable","inputs":{"name":"StrategicPlan","value":{"Region":"@items('Apply_to_each_strategy_plan')?['Region/Value']","StrategicPlan":"@items('Apply_to_each_strategy_plan')?['StrategicPlan']"}}},"Append_to_array_mkt_plan":{"runAfter":{"Append_to_array_strategy_plan":["Succeeded"]},"metadata":{"operationMetadataId":"73995770-aac8-421d-aa9b-92a50bc369bf"},"type":"AppendToArrayVariable","inputs":{"name":"marketPlan","value":{"Region":"@items('Apply_to_each_strategy_plan')?['Region/Value']","MktPlan":"@items('Apply_to_each_strategy_plan')?['MarketingPlan']"}}},"Append_to_array_SalePerson":{"runAfter":{"Append_to_array_mkt_plan":["Succeeded"]},"metadata":{"operationMetadataId":"0f834947-d96c-4ece-b381-e5c3fe7aab5d"},"type":"AppendToArrayVariable","inputs":{"name":"salesPeople","value":{"Region":"@items('Apply_to_each_strategy_plan')?['Region/Value']","Sales":" 销售人员：@{items('Apply_to_each_strategy_plan')?['Sales']} 人 ","AS-NO":"应用专员(AS)和现场服务工程师（FSE）各需要认证总人数：@{coalesce(items('Apply_to_each_strategy_plan')?['AS_x002d_FSE'], 0)} 人","ASCert":"应用专员(AS)和现场服务工程师（FSE）各需要认证总人数:  @{coalesce(items('Apply_to_each_strategy_plan')?['AS_x002d_FSE_x002d_Cert'], 0)}人 ","ASBio":"应用专员(AS)和现场服务工程师（FSE）各需要认证微生物人数：@{coalesce(items('Apply_to_each_strategy_plan')?['AS_x002d_FSE_x002d_Bio'], 0)}人 "}}},"Append_to_array_Device":{"runAfter":{"Append_to_array_SalePerson":["Succeeded"]},"metadata":{"operationMetadataId":"06f68c30-5437-459c-92a9-b2c315c2cdc4"},"type":"AppendToArrayVariable","inputs":{"name":"deviceSales","value":{"Region":"@items('Apply_to_each_strategy_plan')?['Region/Value']","VITEK-MS":" VITEK MS:  @{coalesce(items('Apply_to_each_strategy_plan')?['VITEKMS'],0)} 台","VITEK2":"VITEK 2:  @{coalesce(items('Apply_to_each_strategy_plan')?['VITEK2'], 0)}  台","VITEK2XL":"VITEK 2 XL:  @{coalesce(items('Apply_to_each_strategy_plan')?['VITEK2XL'], 0)}  台","VIRTUO":"VIRTUO:  @{coalesce(items('Apply_to_each_strategy_plan')?['VIRTUO'], 0)}台 ","WASP":"WASP / WASP Lab:  @{coalesce(items('Apply_to_each_strategy_plan')?['WASPWASPLab'], 0)} 台"}}},"Append_to_array_dealSalesTarget":{"runAfter":{"Append_to_array_Device":["Succeeded"]},"metadata":{"operationMetadataId":"fbfbd89e-341e-4ba7-a8f1-a769e082f1e9"},"type":"AppendToArrayVariable","inputs":{"name":"dealerSalesTarget","value":{"region":"@items('Apply_to_each_strategy_plan')?['Region/Value']","regent":"@items('Apply_to_each_strategy_plan')?['regent']","device":"@items('Apply_to_each_strategy_plan')?['DeviceBuget']"}}}},"runAfter":{"Compose_sales_total":["Succeeded"]},"metadata":{"operationMetadataId":"10641c39-8c9f-4361-945f-b7782403128e"},"type":"Foreach"},"Select_StrategicPlan":{"runAfter":{"Select_device":["Succeeded"]},"metadata":{"operationMetadataId":"1a19a813-c6e9-48da-8c37-e4ae3a491d5d"},"type":"Select","inputs":{"from":"@variables('StrategicPlan')","select":{"StrategicPlan":"@item()['StrategicPlan']","Region":"@item()['Region']"}}},"Initialize_marketPlan":{"runAfter":{"Initialize_salesPeople":["Succeeded"]},"metadata":{"operationMetadataId":"b513d37d-e2e5-4082-aeb0-4237e06cdb32"},"type":"InitializeVariable","inputs":{"variables":[{"name":"marketPlan","type":"array"}]}},"Initialize_deviceSales":{"runAfter":{"Initialize_salesBudget":["Succeeded"]},"metadata":{"operationMetadataId":"725f558e-7d21-4f0a-8d95-c14515fa38ce"},"type":"InitializeVariable","inputs":{"variables":[{"name":"deviceSales","type":"array"}]}},"Select_salesperson":{"runAfter":{"Select_StrategicPlan":["Succeeded"]},"metadata":{"operationMetadataId":"520d0100-50bc-4ca4-b54a-faef8798e731"},"type":"Select","inputs":{"from":"@variables('salesPeople')","select":{"Region":"@item()['Region']","Sales":"@item()['Sales']","AS_NO":"@item()['AS-NO']","ASCert":"@item()['ASCert']","ASBio":"@item()['ASBio']"}}},"Select_device":{"runAfter":{"Select_mktplan":["Succeeded"]},"metadata":{"operationMetadataId":"556a67e2-167c-4a2e-a9d0-db6d19518216"},"type":"Select","inputs":{"from":"@variables('deviceSales')","select":{"Region":"@item()['Region']","VITEK_MS":"@item()['VITEK-MS']","VITEK2":"@item()['VITEK2']","VITEK2XL":"@item()['VITEK2XL']","VIRTUO":"@item()['VIRTUO']","WASP":"@item()['WASP']"}}},"Select_mktplan":{"runAfter":{"Apply_to_each_strategy_plan":["Succeeded"]},"metadata":{"operationMetadataId":"77e75f7b-6740-4435-a8d8-2bb0d1cdb28c"},"type":"Select","inputs":{"from":"@variables('marketPlan')","select":{"Region":"@item()['Region']","MktPlan":"@item()['MktPlan']"}}},"Compose_sales_total":{"runAfter":{"Select_sales":["Succeeded"]},"metadata":{"operationMetadataId":"7c111030-60ec-42c7-a6e2-1a0575ef7388"},"type":"Compose","inputs":"@formatNumber(variables('TotalSales'), '0,0.00')"},"Initialize_flowSuccess":{"runAfter":{},"metadata":{"operationMetadataId":"1202b22d-0585-4ce3-a205-6cf4ecfad0b8"},"type":"InitializeVariable","inputs":{"variables":[{"name":"flowSuccess","type":"boolean","value":false}]}},"Populate_a_Microsoft_Word_template_2":{"runAfter":{"Select_dealerSalesTarget":["Succeeded"]},"metadata":{"01PAH2E6374XQW7BXQBZHIS7ISPUJZ3HMG":"/General/wordtemplate/dist-contract-clinic.docx","operationMetadataId":"ad684d3b-0268-4cc2-9481-23165bec3ec5"},"type":"OpenApiConnection","inputs":{"host":{"apiId":"/providers/Microsoft.PowerApps/apis/shared_wordonlinebusiness","connectionName":"shared_wordonlinebusiness","operationId":"CreateFileItem"},"parameters":{"source":"groups/305c9794-3344-474f-b326-710f84600f5a","drive":"b!59f_zl2n2k6EQ0KtYfxLDeap8kR86yFLlWzwPHbH_unl_r4cV90DRpaj78vl370J","file":"01PAH2E6374XQW7BXQBZHIS7ISPUJZ3HMG","dynamicFileSchema/207622086":"@body('Select_brand')","dynamicFileSchema/394851895":"@outputs('Get_Dist')?['body/Title']","dynamicFileSchema/553048279":"@body('Select_device')","dynamicFileSchema/1549184261":"@body('Select_salesperson')","dynamicFileSchema/-143653699":"@outputs('Get_Dist')?['body/Address']","dynamicFileSchema/-1207257961":"@body('Select_contract_item')","dynamicFileSchema/-494031219":"@outputs('Compose_sales_total')","dynamicFileSchema/-1201005306":"@body('Select_sales')","dynamicFileSchema/-1975749389":"@body('Select_StrategicPlan')","dynamicFileSchema/-1963326703":"@body('Select_dealerSalesTarget')","dynamicFileSchema/-1419862344":"@body('Select_mktplan')","dynamicFileSchema/-1585069642":"@body('Select_company')"},"authentication":{"value":"@json(decodeBase64(triggerOutputs().headers['X-MS-APIM-Tokens']))['$ConnectionKey']","type":"Raw"}}},"Initialize_dealerSalesTarget":{"runAfter":{"Initialize_strategic":["Succeeded"]},"metadata":{"operationMetadataId":"5927f6a0-e783-400d-bb94-a511a60c54a4"},"type":"InitializeVariable","inputs":{"variables":[{"name":"dealerSalesTarget","type":"array"}]}},"Select_dealerSalesTarget":{"runAfter":{"Select_salesperson":["Succeeded"]},"metadata":{"operationMetadataId":"7c79d6fb-8170-4638-b2f9-d2a34c2ec000"},"type":"Select","inputs":{"from":"@variables('dealerSalesTarget')","select":{"dealerSalesRegion":"@item()['region']","RegentAmount":"@formatNumber(item()['regent'], '0,0.00')","DeviceAmount":"@formatNumber(item()['device'], '0,0.00')"}}}}},"connectionReferences":{"shared_sharepointonline":{"connectionName":"shared-sharepointonl-c74d3eb8-7ee7-4a42-85ed-3f538e7c9872","source":"Invoker","id":"/providers/Microsoft.PowerApps/apis/shared_sharepointonline","tier":"NotSpecified"},"shared_office365":{"connectionName":"shared-office365-41b624b1-357a-4278-a9bc-da0062995da7","source":"Invoker","id":"/providers/Microsoft.PowerApps/apis/shared_office365","tier":"NotSpecified"},"shared_wordonlinebusiness":{"connectionName":"shared-wordonlinebus-16d7f54f-b8fc-4c23-9926-54b619d8bb02","source":"Invoker","id":"/providers/Microsoft.PowerApps/apis/shared_wordonlinebusiness","tier":"NotSpecified"}},"flowFailureAlertSubscribed":false,"isManaged":false}}